uipath_connectors/microsoft_azureactivedirectory/__init__.py
uipath_connectors/microsoft_azureactivedirectory/client.py
uipath_connectors/microsoft_azureactivedirectory/errors.py
uipath_connectors/microsoft_azureactivedirectory/py.typed
uipath_connectors/microsoft_azureactivedirectory/types.py
uipath_connectors/microsoft_azureactivedirectory/api/__init__.py
uipath_connectors/microsoft_azureactivedirectory/api/directory_roles/__init__.py
uipath_connectors/microsoft_azureactivedirectory/api/directory_roles/list_directory_roles.py
uipath_connectors/microsoft_azureactivedirectory/api/directory_roles_add_member_to_role/__init__.py
uipath_connectors/microsoft_azureactivedirectory/api/directory_roles_add_member_to_role/add_member_to_role.py
uipath_connectors/microsoft_azureactivedirectory/api/directory_roles_is_member_in_role/__init__.py
uipath_connectors/microsoft_azureactivedirectory/api/directory_roles_is_member_in_role/is_member_in_role.py
uipath_connectors/microsoft_azureactivedirectory/api/directory_roles_list_users/__init__.py
uipath_connectors/microsoft_azureactivedirectory/api/directory_roles_list_users/list_users_in_role.py
uipath_connectors/microsoft_azureactivedirectory/api/directory_roles_remove_member_from_role/__init__.py
uipath_connectors/microsoft_azureactivedirectory/api/directory_roles_remove_member_from_role/remove_member_from_role.py
uipath_connectors/microsoft_azureactivedirectory/api/group_add_member_to_group/__init__.py
uipath_connectors/microsoft_azureactivedirectory/api/group_add_member_to_group/add_member_to_group.py
uipath_connectors/microsoft_azureactivedirectory/api/group_lifecycle_policies/__init__.py
uipath_connectors/microsoft_azureactivedirectory/api/group_lifecycle_policies/create_lifecycle_policy.py
uipath_connectors/microsoft_azureactivedirectory/api/group_lifecycle_policies/delete_lifecycle_policy.py
uipath_connectors/microsoft_azureactivedirectory/api/group_lifecycle_policies/lists_lifecycle_policy.py
uipath_connectors_microsoft_azureactivedirectory-1.8.12.dev12.dist-info/METADATA
uipath_connectors_microsoft_azureactivedirectory-1.8.12.dev12.dist-info/WHEEL
uipath_connectors_microsoft_azureactivedirectory-1.8.12.dev12.dist-info/entry_points.txt
uipath_connectors_microsoft_azureactivedirectory-1.8.12.dev12.dist-info/top_level.txt
uipath_connectors_microsoft_azureactivedirectory-1.8.12.dev12.dist-info/RECORD
